byteblowerll/byteblower.py
byteblowerll/__init__.py
byteblowerll/_byteblower.cpython-38-darwin.so
byteblowerll-2.24.0.dist-info/RECORD
byteblowerll-2.24.0.dist-info/WHEEL
byteblowerll-2.24.0.dist-info/top_level.txt
byteblowerll-2.24.0.dist-info/METADATA
