Metadata-Version: 2.1
Name: byteblowerll
Version: 2.24.0
Summary: Python API for the ByteBlower Traffic Generator
Author-email: ByteBlower <support.byteblower@excentis.com>
License: link ../../../../../COPYRIGHT
Project-URL: API Documentation, https://api.byteblower.com
Project-URL: Python example scripts, https://www.github.com/excentis/byteblower_python_examples
Project-URL: Support Portal, https://support.excentis.com
Project-URL: Wireless Endpoint downloads, https://setup.byteblower.com/wirelessendpoints.html
Project-URL: End User License Agreement, https://setup.byteblower.com/byteblower-eula.html
Classifier: Development Status :: 5 - Production/Stable
Classifier: Intended Audience :: Developers
Classifier: Intended Audience :: Telecommunications Industry
Classifier: License :: Other/Proprietary License
Classifier: Programming Language :: Python
Classifier: Programming Language :: Python :: 2
Classifier: Programming Language :: Python :: 2.7
Classifier: Programming Language :: Python :: 3
Classifier: Programming Language :: Python :: 3.7
Classifier: Programming Language :: Python :: 3.8
Classifier: Programming Language :: Python :: 3.9
Classifier: Programming Language :: Python :: 3.10
Classifier: Programming Language :: Python :: 3.11
Classifier: Operating System :: MacOS :: MacOS X
Classifier: Operating System :: Microsoft :: Windows :: Windows 7
Classifier: Operating System :: Microsoft :: Windows :: Windows 8
Classifier: Operating System :: Microsoft :: Windows :: Windows 8.1
Classifier: Operating System :: Microsoft :: Windows :: Windows 10
Classifier: Operating System :: Microsoft :: Windows :: Windows 11
Classifier: Operating System :: POSIX :: Linux
Classifier: Topic :: Software Development :: Testing
Classifier: Topic :: Software Development :: Testing :: Traffic Generation
Classifier: Topic :: Software Development :: Libraries :: Python Modules
License-File: LICENSE
